YuleLog-0.0.3.dist-info/DESCRIPTION.rst
YuleLog-0.0.3.dist-info/METADATA
YuleLog-0.0.3.dist-info/RECORD
YuleLog-0.0.3.dist-info/WHEEL
YuleLog-0.0.3.dist-info/entry_points.txt
YuleLog-0.0.3.dist-info/metadata.json
YuleLog-0.0.3.dist-info/top_level.txt
yule_log/__init__.py
yule_log/__main__.py
yule_log/fire.py
