Metadata-Version: 2.0
Name: YuleLog
Version: 0.0.3
Summary: Terminal based X-Mas Yule Log Fireplace
Home-page: https://github.com/Duroktar/YuleLog
Author: Scott Doucet
Author-email: duroktar@gmail.com
License: MIT License
Keywords: christmas yule fireplace
Platform: UNKNOWN
Classifier: Development Status :: 3 - Alpha
Classifier: Intended Audience :: End Users/Desktop
Classifier: Topic :: Games/Entertainment
Classifier: License :: OSI Approved :: MIT License
Classifier: Programming Language :: Python :: 2
Classifier: Programming Language :: Python :: 2.7
Classifier: Programming Language :: Python :: 3
Classifier: Programming Language :: Python :: 3.5
Classifier: Programming Language :: Python :: 3.6
Requires-Dist: asciimatics (==1.7.2)
Requires-Dist: Pillow (==3.4.2)
Requires-Dist: pyfiglet (==0.7.5)
